[
    {
        "name": "SecretLegendary",
        "category": "SecretLegendary",
        "tID": "???",
        "rarity": null,
        "disabled": null,
        "resource": "Diamonds",
        "cost": 500,
        "count": null,
        "cycleDuration": 21,
        "cycleDeadzoneStart": 7,
        "cycleDeadzoneEnd": null,
        "topSection": null,
        "specialOffer": "TRUE",
        "durationSecs": null,
        "availabilitySecs": null,
        "syncToShopCycle": null,
        "chest": "Legendary",
        "trophyLimit": 1400,
        "iAP": null,
        "starterPack_Chest": null,
        "starterPack_Gold": null,
        "valueMultiplier": null,
        "appendArenaToChestName": null,
        "tiedToArenaUnlock": null,
        "repeatPurchaseGemPackOverride": null,
        "eventName": null,
        "costAdjustBasedOnChestContents": null,
        "isChronosOffer": null
    },
    {
        "name": "SecretEpic",
        "category": "SecretEpic",
        "tID": "???",
        "rarity": null,
        "disabled": null,
        "resource": "Gold",
        "cost": 10000,
        "count": null,
        "cycleDuration": 14,
        "cycleDeadzoneStart": null,
        "cycleDeadzoneEnd": 3,
        "topSection": null,
        "specialOffer": "TRUE",
        "durationSecs": null,
        "availabilitySecs": null,
        "syncToShopCycle": null,
        "chest": "Epic",
        "trophyLimit": 1000,
        "iAP": null,
        "starterPack_Chest": null,
        "starterPack_Gold": null,
        "valueMultiplier": null,
        "appendArenaToChestName": "TRUE",
        "tiedToArenaUnlock": null,
        "repeatPurchaseGemPackOverride": null,
        "eventName": null,
        "costAdjustBasedOnChestContents": "TRUE",
        "isChronosOffer": null
    },
    {
        "name": "Spell",
        "category": "Spell",
        "tID": null,
        "rarity": null,
        "disabled": null,
        "resource": null,
        "cost": null,
        "count": null,
        "cycleDuration": null,
        "cycleDeadzoneStart": null,
        "cycleDeadzoneEnd": null,
        "topSection": "TRUE",
        "specialOffer": null,
        "durationSecs": null,
        "availabilitySecs": null,
        "syncToShopCycle": null,
        "chest": null,
        "trophyLimit": null,
        "iAP": null,
        "starterPack_Chest": null,
        "starterPack_Gold": null,
        "valueMultiplier": null,
        "appendArenaToChestName": null,
        "tiedToArenaUnlock": null,
        "repeatPurchaseGemPackOverride": null,
        "eventName": null,
        "costAdjustBasedOnChestContents": null,
        "isChronosOffer": null
    },
    {
        "name": "Chest",
        "category": "Chest",
        "tID": null,
        "rarity": null,
        "disabled": null,
        "resource": null,
        "cost": null,
        "count": null,
        "cycleDuration": null,
        "cycleDeadzoneStart": null,
        "cycleDeadzoneEnd": null,
        "topSection": null,
        "specialOffer": null,
        "durationSecs": null,
        "availabilitySecs": null,
        "syncToShopCycle": null,
        "chest": null,
        "trophyLimit": null,
        "iAP": null,
        "starterPack_Chest": null,
        "starterPack_Gold": null,
        "valueMultiplier": null,
        "appendArenaToChestName": null,
        "tiedToArenaUnlock": null,
        "repeatPurchaseGemPackOverride": null,
        "eventName": null,
        "costAdjustBasedOnChestContents": null,
        "isChronosOffer": null
    },
    {
        "name": "ResourceGold",
        "category": "Gold",
        "tID": null,
        "rarity": null,
        "disabled": null,
        "resource": null,
        "cost": null,
        "count": null,
        "cycleDuration": null,
        "cycleDeadzoneStart": null,
        "cycleDeadzoneEnd": null,
        "topSection": null,
        "specialOffer": null,
        "durationSecs": null,
        "availabilitySecs": null,
        "syncToShopCycle": null,
        "chest": null,
        "trophyLimit": null,
        "iAP": null,
        "starterPack_Chest": null,
        "starterPack_Gold": null,
        "valueMultiplier": null,
        "appendArenaToChestName": null,
        "tiedToArenaUnlock": null,
        "repeatPurchaseGemPackOverride": null,
        "eventName": null,
        "costAdjustBasedOnChestContents": null,
        "isChronosOffer": null
    },
    {
        "name": "ResourceDiamond",
        "category": "Diamond",
        "tID": null,
        "rarity": null,
        "disabled": null,
        "resource": null,
        "cost": null,
        "count": null,
        "cycleDuration": null,
        "cycleDeadzoneStart": null,
        "cycleDeadzoneEnd": null,
        "topSection": null,
        "specialOffer": null,
        "durationSecs": null,
        "availabilitySecs": null,
        "syncToShopCycle": null,
        "chest": null,
        "trophyLimit": null,
        "iAP": null,
        "starterPack_Chest": null,
        "starterPack_Gold": null,
        "valueMultiplier": null,
        "appendArenaToChestName": null,
        "tiedToArenaUnlock": null,
        "repeatPurchaseGemPackOverride": null,
        "eventName": null,
        "costAdjustBasedOnChestContents": null,
        "isChronosOffer": null
    },
    {
        "name": "REMOVED9",
        "category": "NOTINUSE",
        "tID": null,
        "rarity": null,
        "disabled": null,
        "resource": null,
        "cost": null,
        "count": null,
        "cycleDuration": null,
        "cycleDeadzoneStart": null,
        "cycleDeadzoneEnd": null,
        "topSection": null,
        "specialOffer": null,
        "durationSecs": null,
        "availabilitySecs": null,
        "syncToShopCycle": null,
        "chest": null,
        "trophyLimit": null,
        "iAP": null,
        "starterPack_Chest": null,
        "starterPack_Gold": null,
        "valueMultiplier": null,
        "appendArenaToChestName": null,
        "tiedToArenaUnlock": null,
        "repeatPurchaseGemPackOverride": null,
        "eventName": null,
        "costAdjustBasedOnChestContents": null,
        "isChronosOffer": null
    },
    {
        "name": "REMOVED10",
        "category": "NOTINUSE",
        "tID": null,
        "rarity": null,
        "disabled": null,
        "resource": null,
        "cost": null,
        "count": null,
        "cycleDuration": null,
        "cycleDeadzoneStart": null,
        "cycleDeadzoneEnd": null,
        "topSection": null,
        "specialOffer": null,
        "durationSecs": null,
        "availabilitySecs": null,
        "syncToShopCycle": null,
        "chest": null,
        "trophyLimit": null,
        "iAP": null,
        "starterPack_Chest": null,
        "starterPack_Gold": null,
        "valueMultiplier": null,
        "appendArenaToChestName": null,
        "tiedToArenaUnlock": null,
        "repeatPurchaseGemPackOverride": null,
        "eventName": null,
        "costAdjustBasedOnChestContents": null,
        "isChronosOffer": null
    },
    {
        "name": "REMOVED11",
        "category": "NOTINUSE",
        "tID": null,
        "rarity": null,
        "disabled": null,
        "resource": null,
        "cost": null,
        "count": null,
        "cycleDuration": null,
        "cycleDeadzoneStart": null,
        "cycleDeadzoneEnd": null,
        "topSection": null,
        "specialOffer": null,
        "durationSecs": null,
        "availabilitySecs": null,
        "syncToShopCycle": null,
        "chest": null,
        "trophyLimit": null,
        "iAP": null,
        "starterPack_Chest": null,
        "starterPack_Gold": null,
        "valueMultiplier": null,
        "appendArenaToChestName": null,
        "tiedToArenaUnlock": null,
        "repeatPurchaseGemPackOverride": null,
        "eventName": null,
        "costAdjustBasedOnChestContents": null,
        "isChronosOffer": null
    },
    {
        "name": "StarterPackArena3",
        "category": "StarterPack",
        "tID": "Starter Pack Arena 3",
        "rarity": null,
        "disabled": null,
        "resource": "IAP",
        "cost": null,
        "count": null,
        "cycleDuration": 14,
        "cycleDeadzoneStart": 5,
        "cycleDeadzoneEnd": 5,
        "topSection": null,
        "specialOffer": "TRUE",
        "durationSecs": null,
        "availabilitySecs": null,
        "syncToShopCycle": null,
        "chest": null,
        "trophyLimit": 800,
        "iAP": "com.supercell.scroll.consumablestarterpack0",
        "starterPack_Chest": "Shop_Small_1_Arena3",
        "starterPack_Gold": 2000,
        "valueMultiplier": 4,
        "appendArenaToChestName": null,
        "tiedToArenaUnlock": null,
        "repeatPurchaseGemPackOverride": null,
        "eventName": null,
        "costAdjustBasedOnChestContents": null,
        "isChronosOffer": null
    },
    {
        "name": "StarterPackArena4",
        "category": "StarterPack",
        "tID": "Starter Pack Arena 4",
        "rarity": null,
        "disabled": null,
        "resource": "IAP",
        "cost": null,
        "count": null,
        "cycleDuration": 14,
        "cycleDeadzoneStart": 5,
        "cycleDeadzoneEnd": 5,
        "topSection": null,
        "specialOffer": "TRUE",
        "durationSecs": null,
        "availabilitySecs": null,
        "syncToShopCycle": null,
        "chest": null,
        "trophyLimit": 1100,
        "iAP": "com.supercell.scroll.consumablestarterpack1",
        "starterPack_Chest": "Shop_Small_1_Arena4",
        "starterPack_Gold": 2000,
        "valueMultiplier": 4,
        "appendArenaToChestName": null,
        "tiedToArenaUnlock": null,
        "repeatPurchaseGemPackOverride": null,
        "eventName": null,
        "costAdjustBasedOnChestContents": null,
        "isChronosOffer": null
    },
    {
        "name": "StarterPackArena5",
        "category": "StarterPack",
        "tID": "Starter Pack Arena 5",
        "rarity": null,
        "disabled": null,
        "resource": "IAP",
        "cost": null,
        "count": null,
        "cycleDuration": 14,
        "cycleDeadzoneStart": 5,
        "cycleDeadzoneEnd": 5,
        "topSection": null,
        "specialOffer": "TRUE",
        "durationSecs": null,
        "availabilitySecs": null,
        "syncToShopCycle": null,
        "chest": null,
        "trophyLimit": 1400,
        "iAP": "com.supercell.scroll.consumablestarterpack2",
        "starterPack_Chest": "Shop_Large_Arena5",
        "starterPack_Gold": 5000,
        "valueMultiplier": 4,
        "appendArenaToChestName": null,
        "tiedToArenaUnlock": null,
        "repeatPurchaseGemPackOverride": null,
        "eventName": null,
        "costAdjustBasedOnChestContents": null,
        "isChronosOffer": null
    },
    {
        "name": "StarterPackArena6",
        "category": "StarterPack",
        "tID": "Starter Pack Arena 6",
        "rarity": null,
        "disabled": null,
        "resource": "IAP",
        "cost": null,
        "count": null,
        "cycleDuration": 14,
        "cycleDeadzoneStart": 5,
        "cycleDeadzoneEnd": 5,
        "topSection": null,
        "specialOffer": "TRUE",
        "durationSecs": null,
        "availabilitySecs": null,
        "syncToShopCycle": null,
        "chest": null,
        "trophyLimit": 1700,
        "iAP": "com.supercell.scroll.consumablestarterpack3",
        "starterPack_Chest": "Shop_Large_Arena6",
        "starterPack_Gold": 5000,
        "valueMultiplier": 4,
        "appendArenaToChestName": null,
        "tiedToArenaUnlock": null,
        "repeatPurchaseGemPackOverride": null,
        "eventName": null,
        "costAdjustBasedOnChestContents": null,
        "isChronosOffer": null
    },
    {
        "name": "StarterPackArena7",
        "category": "StarterPack",
        "tID": "Starter Pack Arena 7",
        "rarity": null,
        "disabled": null,
        "resource": "IAP",
        "cost": null,
        "count": null,
        "cycleDuration": 14,
        "cycleDeadzoneStart": 5,
        "cycleDeadzoneEnd": 5,
        "topSection": null,
        "specialOffer": "TRUE",
        "durationSecs": null,
        "availabilitySecs": null,
        "syncToShopCycle": null,
        "chest": null,
        "trophyLimit": 2000,
        "iAP": "com.supercell.scroll.consumablestarterpack4",
        "starterPack_Chest": "Shop_Large_Legendary_Arena7",
        "starterPack_Gold": 50000,
        "valueMultiplier": 4,
        "appendArenaToChestName": null,
        "tiedToArenaUnlock": null,
        "repeatPurchaseGemPackOverride": null,
        "eventName": null,
        "costAdjustBasedOnChestContents": null,
        "isChronosOffer": null
    },
    {
        "name": "StarterPackArena8",
        "category": "StarterPack",
        "tID": "Starter Pack Arena 8",
        "rarity": null,
        "disabled": null,
        "resource": "IAP",
        "cost": null,
        "count": null,
        "cycleDuration": 14,
        "cycleDeadzoneStart": 5,
        "cycleDeadzoneEnd": 5,
        "topSection": null,
        "specialOffer": "TRUE",
        "durationSecs": null,
        "availabilitySecs": null,
        "syncToShopCycle": null,
        "chest": null,
        "trophyLimit": 2300,
        "iAP": "com.supercell.scroll.consumablestarterpack5",
        "starterPack_Chest": "Shop_Large_Legendary_Arena8",
        "starterPack_Gold": 50000,
        "valueMultiplier": 4,
        "appendArenaToChestName": null,
        "tiedToArenaUnlock": null,
        "repeatPurchaseGemPackOverride": null,
        "eventName": null,
        "costAdjustBasedOnChestContents": null,
        "isChronosOffer": null
    },
    {
        "name": "StarterPackArenaL",
        "category": "StarterPack",
        "tID": "Starter Pack Legendary Arena",
        "rarity": null,
        "disabled": null,
        "resource": "IAP",
        "cost": null,
        "count": null,
        "cycleDuration": 14,
        "cycleDeadzoneStart": 5,
        "cycleDeadzoneEnd": 5,
        "topSection": null,
        "specialOffer": "TRUE",
        "durationSecs": null,
        "availabilitySecs": null,
        "syncToShopCycle": null,
        "chest": null,
        "trophyLimit": 3000,
        "iAP": "com.supercell.scroll.consumablestarterpack6",
        "starterPack_Chest": "Shop_Large_Legendary_Arena_L",
        "starterPack_Gold": 50000,
        "valueMultiplier": 4,
        "appendArenaToChestName": null,
        "tiedToArenaUnlock": null,
        "repeatPurchaseGemPackOverride": null,
        "eventName": null,
        "costAdjustBasedOnChestContents": null,
        "isChronosOffer": null
    },
    {
        "name": "Red",
        "category": "NOTINUSE",
        "tID": "Magical Gem Pack",
        "rarity": null,
        "disabled": "TRUE",
        "resource": null,
        "cost": null,
        "count": null,
        "cycleDuration": null,
        "cycleDeadzoneStart": null,
        "cycleDeadzoneEnd": null,
        "topSection": null,
        "specialOffer": null,
        "durationSecs": null,
        "availabilitySecs": null,
        "syncToShopCycle": null,
        "chest": null,
        "trophyLimit": null,
        "iAP": "com.supercell.scroll.red",
        "starterPack_Chest": null,
        "starterPack_Gold": null,
        "valueMultiplier": null,
        "appendArenaToChestName": null,
        "tiedToArenaUnlock": null,
        "repeatPurchaseGemPackOverride": null,
        "eventName": null,
        "costAdjustBasedOnChestContents": null,
        "isChronosOffer": null
    },
    {
        "name": "RumbleBundle0",
        "category": "NOTINUSE",
        "tID": "Magical Gem Pack",
        "rarity": null,
        "disabled": "TRUE",
        "resource": null,
        "cost": null,
        "count": null,
        "cycleDuration": null,
        "cycleDeadzoneStart": null,
        "cycleDeadzoneEnd": null,
        "topSection": null,
        "specialOffer": null,
        "durationSecs": null,
        "availabilitySecs": null,
        "syncToShopCycle": null,
        "chest": null,
        "trophyLimit": null,
        "iAP": "com.supercell.scroll.rumblebundle0",
        "starterPack_Chest": null,
        "starterPack_Gold": null,
        "valueMultiplier": null,
        "appendArenaToChestName": null,
        "tiedToArenaUnlock": null,
        "repeatPurchaseGemPackOverride": null,
        "eventName": null,
        "costAdjustBasedOnChestContents": null,
        "isChronosOffer": null
    },
    {
        "name": "RumbleBundle1",
        "category": "NOTINUSE",
        "tID": "Gold and Gem Pack",
        "rarity": null,
        "disabled": "TRUE",
        "resource": null,
        "cost": null,
        "count": null,
        "cycleDuration": null,
        "cycleDeadzoneStart": null,
        "cycleDeadzoneEnd": null,
        "topSection": null,
        "specialOffer": null,
        "durationSecs": null,
        "availabilitySecs": null,
        "syncToShopCycle": null,
        "chest": null,
        "trophyLimit": null,
        "iAP": "com.supercell.scroll.rumblebundle1",
        "starterPack_Chest": null,
        "starterPack_Gold": null,
        "valueMultiplier": null,
        "appendArenaToChestName": null,
        "tiedToArenaUnlock": null,
        "repeatPurchaseGemPackOverride": null,
        "eventName": null,
        "costAdjustBasedOnChestContents": null,
        "isChronosOffer": null
    },
    {
        "name": "RumbleBundle2",
        "category": "NOTINUSE",
        "tID": "Super Magical Gem Pack",
        "rarity": null,
        "disabled": "TRUE",
        "resource": null,
        "cost": null,
        "count": null,
        "cycleDuration": null,
        "cycleDeadzoneStart": null,
        "cycleDeadzoneEnd": null,
        "topSection": null,
        "specialOffer": null,
        "durationSecs": null,
        "availabilitySecs": null,
        "syncToShopCycle": null,
        "chest": null,
        "trophyLimit": null,
        "iAP": "com.supercell.scroll.rumblebundle2",
        "starterPack_Chest": null,
        "starterPack_Gold": null,
        "valueMultiplier": null,
        "appendArenaToChestName": null,
        "tiedToArenaUnlock": null,
        "repeatPurchaseGemPackOverride": null,
        "eventName": null,
        "costAdjustBasedOnChestContents": null,
        "isChronosOffer": null
    },
    {
        "name": "REMOVED1",
        "category": "NOTINUSE",
        "tID": null,
        "rarity": null,
        "disabled": null,
        "resource": null,
        "cost": null,
        "count": null,
        "cycleDuration": null,
        "cycleDeadzoneStart": null,
        "cycleDeadzoneEnd": null,
        "topSection": null,
        "specialOffer": null,
        "durationSecs": null,
        "availabilitySecs": null,
        "syncToShopCycle": null,
        "chest": null,
        "trophyLimit": null,
        "iAP": null,
        "starterPack_Chest": null,
        "starterPack_Gold": null,
        "valueMultiplier": null,
        "appendArenaToChestName": null,
        "tiedToArenaUnlock": null,
        "repeatPurchaseGemPackOverride": null,
        "eventName": null,
        "costAdjustBasedOnChestContents": null,
        "isChronosOffer": null
    },
    {
        "name": "REMOVED2",
        "category": "NOTINUSE",
        "tID": null,
        "rarity": null,
        "disabled": null,
        "resource": null,
        "cost": null,
        "count": null,
        "cycleDuration": null,
        "cycleDeadzoneStart": null,
        "cycleDeadzoneEnd": null,
        "topSection": null,
        "specialOffer": null,
        "durationSecs": null,
        "availabilitySecs": null,
        "syncToShopCycle": null,
        "chest": null,
        "trophyLimit": null,
        "iAP": null,
        "starterPack_Chest": null,
        "starterPack_Gold": null,
        "valueMultiplier": null,
        "appendArenaToChestName": null,
        "tiedToArenaUnlock": null,
        "repeatPurchaseGemPackOverride": null,
        "eventName": null,
        "costAdjustBasedOnChestContents": null,
        "isChronosOffer": null
    },
    {
        "name": "REMOVED3",
        "category": "NOTINUSE",
        "tID": null,
        "rarity": null,
        "disabled": null,
        "resource": null,
        "cost": null,
        "count": null,
        "cycleDuration": null,
        "cycleDeadzoneStart": null,
        "cycleDeadzoneEnd": null,
        "topSection": null,
        "specialOffer": null,
        "durationSecs": null,
        "availabilitySecs": null,
        "syncToShopCycle": null,
        "chest": null,
        "trophyLimit": null,
        "iAP": null,
        "starterPack_Chest": null,
        "starterPack_Gold": null,
        "valueMultiplier": null,
        "appendArenaToChestName": null,
        "tiedToArenaUnlock": null,
        "repeatPurchaseGemPackOverride": null,
        "eventName": null,
        "costAdjustBasedOnChestContents": null,
        "isChronosOffer": null
    },
    {
        "name": "REMOVED4",
        "category": "NOTINUSE",
        "tID": null,
        "rarity": null,
        "disabled": null,
        "resource": null,
        "cost": null,
        "count": null,
        "cycleDuration": null,
        "cycleDeadzoneStart": null,
        "cycleDeadzoneEnd": null,
        "topSection": null,
        "specialOffer": null,
        "durationSecs": null,
        "availabilitySecs": null,
        "syncToShopCycle": null,
        "chest": null,
        "trophyLimit": null,
        "iAP": null,
        "starterPack_Chest": null,
        "starterPack_Gold": null,
        "valueMultiplier": null,
        "appendArenaToChestName": null,
        "tiedToArenaUnlock": null,
        "repeatPurchaseGemPackOverride": null,
        "eventName": null,
        "costAdjustBasedOnChestContents": null,
        "isChronosOffer": null
    },
    {
        "name": "REMOVED5",
        "category": "NOTINUSE",
        "tID": null,
        "rarity": null,
        "disabled": null,
        "resource": null,
        "cost": null,
        "count": null,
        "cycleDuration": null,
        "cycleDeadzoneStart": null,
        "cycleDeadzoneEnd": null,
        "topSection": null,
        "specialOffer": null,
        "durationSecs": null,
        "availabilitySecs": null,
        "syncToShopCycle": null,
        "chest": null,
        "trophyLimit": null,
        "iAP": null,
        "starterPack_Chest": null,
        "starterPack_Gold": null,
        "valueMultiplier": null,
        "appendArenaToChestName": null,
        "tiedToArenaUnlock": null,
        "repeatPurchaseGemPackOverride": null,
        "eventName": null,
        "costAdjustBasedOnChestContents": null,
        "isChronosOffer": null
    },
    {
        "name": "REMOVED6",
        "category": "NOTINUSE",
        "tID": null,
        "rarity": null,
        "disabled": null,
        "resource": null,
        "cost": null,
        "count": null,
        "cycleDuration": null,
        "cycleDeadzoneStart": null,
        "cycleDeadzoneEnd": null,
        "topSection": null,
        "specialOffer": null,
        "durationSecs": null,
        "availabilitySecs": null,
        "syncToShopCycle": null,
        "chest": null,
        "trophyLimit": null,
        "iAP": null,
        "starterPack_Chest": null,
        "starterPack_Gold": null,
        "valueMultiplier": null,
        "appendArenaToChestName": null,
        "tiedToArenaUnlock": null,
        "repeatPurchaseGemPackOverride": null,
        "eventName": null,
        "costAdjustBasedOnChestContents": null,
        "isChronosOffer": null
    },
    {
        "name": "REMOVED7",
        "category": "NOTINUSE",
        "tID": null,
        "rarity": null,
        "disabled": null,
        "resource": null,
        "cost": null,
        "count": null,
        "cycleDuration": null,
        "cycleDeadzoneStart": null,
        "cycleDeadzoneEnd": null,
        "topSection": null,
        "specialOffer": null,
        "durationSecs": null,
        "availabilitySecs": null,
        "syncToShopCycle": null,
        "chest": null,
        "trophyLimit": null,
        "iAP": null,
        "starterPack_Chest": null,
        "starterPack_Gold": null,
        "valueMultiplier": null,
        "appendArenaToChestName": null,
        "tiedToArenaUnlock": null,
        "repeatPurchaseGemPackOverride": null,
        "eventName": null,
        "costAdjustBasedOnChestContents": null,
        "isChronosOffer": null
    },
    {
        "name": "REMOVED8",
        "category": "NOTINUSE",
        "tID": null,
        "rarity": null,
        "disabled": null,
        "resource": null,
        "cost": null,
        "count": null,
        "cycleDuration": null,
        "cycleDeadzoneStart": null,
        "cycleDeadzoneEnd": null,
        "topSection": null,
        "specialOffer": null,
        "durationSecs": null,
        "availabilitySecs": null,
        "syncToShopCycle": null,
        "chest": null,
        "trophyLimit": null,
        "iAP": null,
        "starterPack_Chest": null,
        "starterPack_Gold": null,
        "valueMultiplier": null,
        "appendArenaToChestName": null,
        "tiedToArenaUnlock": null,
        "repeatPurchaseGemPackOverride": null,
        "eventName": null,
        "costAdjustBasedOnChestContents": null,
        "isChronosOffer": null
    },
    {
        "name": "StarterPackArena9",
        "category": "StarterPack",
        "tID": "Jungle Arena Pack",
        "rarity": null,
        "disabled": null,
        "resource": "IAP",
        "cost": null,
        "count": null,
        "cycleDuration": 14,
        "cycleDeadzoneStart": 5,
        "cycleDeadzoneEnd": 5,
        "topSection": null,
        "specialOffer": "TRUE",
        "durationSecs": null,
        "availabilitySecs": null,
        "syncToShopCycle": null,
        "chest": null,
        "trophyLimit": 2600,
        "iAP": "com.supercell.scroll.consumablestarterpack7",
        "starterPack_Chest": "Shop_Large_Legendary_Arena9",
        "starterPack_Gold": 50000,
        "valueMultiplier": 4,
        "appendArenaToChestName": null,
        "tiedToArenaUnlock": "Arena9",
        "repeatPurchaseGemPackOverride": null,
        "eventName": null,
        "costAdjustBasedOnChestContents": null,
        "isChronosOffer": null
    },
    {
        "name": "HolidayBundle0",
        "category": "NOTINUSE",
        "tID": "Holiday Pack 1",
        "rarity": null,
        "disabled": "TRUE",
        "resource": null,
        "cost": null,
        "count": null,
        "cycleDuration": null,
        "cycleDeadzoneStart": null,
        "cycleDeadzoneEnd": null,
        "topSection": null,
        "specialOffer": null,
        "durationSecs": null,
        "availabilitySecs": null,
        "syncToShopCycle": null,
        "chest": null,
        "trophyLimit": null,
        "iAP": "com.supercell.scroll.consumableholidaypack0",
        "starterPack_Chest": null,
        "starterPack_Gold": null,
        "valueMultiplier": null,
        "appendArenaToChestName": null,
        "tiedToArenaUnlock": null,
        "repeatPurchaseGemPackOverride": null,
        "eventName": null,
        "costAdjustBasedOnChestContents": null,
        "isChronosOffer": null
    },
    {
        "name": "HolidayBundle1",
        "category": "NOTINUSE",
        "tID": "Holiday Pack 2",
        "rarity": null,
        "disabled": "TRUE",
        "resource": null,
        "cost": null,
        "count": null,
        "cycleDuration": null,
        "cycleDeadzoneStart": null,
        "cycleDeadzoneEnd": null,
        "topSection": null,
        "specialOffer": null,
        "durationSecs": null,
        "availabilitySecs": null,
        "syncToShopCycle": null,
        "chest": null,
        "trophyLimit": null,
        "iAP": "com.supercell.scroll.consumableholidaypack1",
        "starterPack_Chest": null,
        "starterPack_Gold": null,
        "valueMultiplier": null,
        "appendArenaToChestName": null,
        "tiedToArenaUnlock": null,
        "repeatPurchaseGemPackOverride": null,
        "eventName": null,
        "costAdjustBasedOnChestContents": null,
        "isChronosOffer": null
    },
    {
        "name": "HolidayBundle2",
        "category": "NOTINUSE",
        "tID": "Holiday Pack 3",
        "rarity": null,
        "disabled": "TRUE",
        "resource": null,
        "cost": null,
        "count": null,
        "cycleDuration": null,
        "cycleDeadzoneStart": null,
        "cycleDeadzoneEnd": null,
        "topSection": null,
        "specialOffer": null,
        "durationSecs": null,
        "availabilitySecs": null,
        "syncToShopCycle": null,
        "chest": null,
        "trophyLimit": null,
        "iAP": "com.supercell.scroll.consumableholidaypack2",
        "starterPack_Chest": null,
        "starterPack_Gold": null,
        "valueMultiplier": null,
        "appendArenaToChestName": null,
        "tiedToArenaUnlock": null,
        "repeatPurchaseGemPackOverride": null,
        "eventName": null,
        "costAdjustBasedOnChestContents": null,
        "isChronosOffer": null
    },
    {
        "name": "ChineseNewYearBundle0",
        "category": "NOTINUSE",
        "tID": "Gold and Gem Pack",
        "rarity": null,
        "disabled": "TRUE",
        "resource": null,
        "cost": null,
        "count": null,
        "cycleDuration": null,
        "cycleDeadzoneStart": null,
        "cycleDeadzoneEnd": null,
        "topSection": null,
        "specialOffer": null,
        "durationSecs": null,
        "availabilitySecs": null,
        "syncToShopCycle": null,
        "chest": null,
        "trophyLimit": null,
        "iAP": "com.supercell.scroll.consumablechinesenewyear0",
        "starterPack_Chest": null,
        "starterPack_Gold": null,
        "valueMultiplier": null,
        "appendArenaToChestName": null,
        "tiedToArenaUnlock": null,
        "repeatPurchaseGemPackOverride": null,
        "eventName": null,
        "costAdjustBasedOnChestContents": null,
        "isChronosOffer": null
    },
    {
        "name": "ChineseNewYearBundle1",
        "category": "NOTINUSE",
        "tID": "Magical Gem Pack",
        "rarity": null,
        "disabled": "TRUE",
        "resource": null,
        "cost": null,
        "count": null,
        "cycleDuration": null,
        "cycleDeadzoneStart": null,
        "cycleDeadzoneEnd": null,
        "topSection": null,
        "specialOffer": null,
        "durationSecs": null,
        "availabilitySecs": null,
        "syncToShopCycle": null,
        "chest": null,
        "trophyLimit": null,
        "iAP": "com.supercell.scroll.consumablechinesenewyear1",
        "starterPack_Chest": null,
        "starterPack_Gold": null,
        "valueMultiplier": null,
        "appendArenaToChestName": null,
        "tiedToArenaUnlock": null,
        "repeatPurchaseGemPackOverride": null,
        "eventName": null,
        "costAdjustBasedOnChestContents": null,
        "isChronosOffer": null
    },
    {
        "name": "ChineseNewYearBundle2",
        "category": "NOTINUSE",
        "tID": "Super Magical Gem Pack",
        "rarity": null,
        "disabled": "TRUE",
        "resource": null,
        "cost": null,
        "count": null,
        "cycleDuration": null,
        "cycleDeadzoneStart": null,
        "cycleDeadzoneEnd": null,
        "topSection": null,
        "specialOffer": null,
        "durationSecs": null,
        "availabilitySecs": null,
        "syncToShopCycle": null,
        "chest": null,
        "trophyLimit": null,
        "iAP": "com.supercell.scroll.consumablechinesenewyear2",
        "starterPack_Chest": null,
        "starterPack_Gold": null,
        "valueMultiplier": null,
        "appendArenaToChestName": null,
        "tiedToArenaUnlock": null,
        "repeatPurchaseGemPackOverride": null,
        "eventName": null,
        "costAdjustBasedOnChestContents": null,
        "isChronosOffer": null
    },
    {
        "name": "ChronosOffer_1",
        "category": "Chronos",
        "tID": "Special Offer",
        "rarity": null,
        "disabled": null,
        "resource": null,
        "cost": null,
        "count": null,
        "cycleDuration": null,
        "cycleDeadzoneStart": null,
        "cycleDeadzoneEnd": null,
        "topSection": null,
        "specialOffer": null,
        "durationSecs": null,
        "availabilitySecs": null,
        "syncToShopCycle": null,
        "chest": null,
        "trophyLimit": null,
        "iAP": "com.supercell.scroll.specialoffertier1",
        "starterPack_Chest": null,
        "starterPack_Gold": null,
        "valueMultiplier": null,
        "appendArenaToChestName": null,
        "tiedToArenaUnlock": null,
        "repeatPurchaseGemPackOverride": null,
        "eventName": null,
        "costAdjustBasedOnChestContents": null,
        "isChronosOffer": "TRUE"
    },
    {
        "name": "ChronosOffer_2",
        "category": "Chronos",
        "tID": "Special Offer",
        "rarity": null,
        "disabled": null,
        "resource": null,
        "cost": null,
        "count": null,
        "cycleDuration": null,
        "cycleDeadzoneStart": null,
        "cycleDeadzoneEnd": null,
        "topSection": null,
        "specialOffer": null,
        "durationSecs": null,
        "availabilitySecs": null,
        "syncToShopCycle": null,
        "chest": null,
        "trophyLimit": null,
        "iAP": "com.supercell.scroll.specialoffertier2",
        "starterPack_Chest": null,
        "starterPack_Gold": null,
        "valueMultiplier": null,
        "appendArenaToChestName": null,
        "tiedToArenaUnlock": null,
        "repeatPurchaseGemPackOverride": null,
        "eventName": null,
        "costAdjustBasedOnChestContents": null,
        "isChronosOffer": "TRUE"
    },
    {
        "name": "ChronosOffer_3",
        "category": "Chronos",
        "tID": "Special Offer",
        "rarity": null,
        "disabled": null,
        "resource": null,
        "cost": null,
        "count": null,
        "cycleDuration": null,
        "cycleDeadzoneStart": null,
        "cycleDeadzoneEnd": null,
        "topSection": null,
        "specialOffer": null,
        "durationSecs": null,
        "availabilitySecs": null,
        "syncToShopCycle": null,
        "chest": null,
        "trophyLimit": null,
        "iAP": "com.supercell.scroll.specialoffertier3",
        "starterPack_Chest": null,
        "starterPack_Gold": null,
        "valueMultiplier": null,
        "appendArenaToChestName": null,
        "tiedToArenaUnlock": null,
        "repeatPurchaseGemPackOverride": null,
        "eventName": null,
        "costAdjustBasedOnChestContents": null,
        "isChronosOffer": "TRUE"
    },
    {
        "name": "ChronosOffer_4",
        "category": "Chronos",
        "tID": "Special Offer",
        "rarity": null,
        "disabled": null,
        "resource": null,
        "cost": null,
        "count": null,
        "cycleDuration": null,
        "cycleDeadzoneStart": null,
        "cycleDeadzoneEnd": null,
        "topSection": null,
        "specialOffer": null,
        "durationSecs": null,
        "availabilitySecs": null,
        "syncToShopCycle": null,
        "chest": null,
        "trophyLimit": null,
        "iAP": "com.supercell.scroll.specialoffertier4",
        "starterPack_Chest": null,
        "starterPack_Gold": null,
        "valueMultiplier": null,
        "appendArenaToChestName": null,
        "tiedToArenaUnlock": null,
        "repeatPurchaseGemPackOverride": null,
        "eventName": null,
        "costAdjustBasedOnChestContents": null,
        "isChronosOffer": "TRUE"
    },
    {
        "name": "ChronosOffer_5",
        "category": "Chronos",
        "tID": "Special Offer",
        "rarity": null,
        "disabled": null,
        "resource": null,
        "cost": null,
        "count": null,
        "cycleDuration": null,
        "cycleDeadzoneStart": null,
        "cycleDeadzoneEnd": null,
        "topSection": null,
        "specialOffer": null,
        "durationSecs": null,
        "availabilitySecs": null,
        "syncToShopCycle": null,
        "chest": null,
        "trophyLimit": null,
        "iAP": "com.supercell.scroll.specialoffertier5",
        "starterPack_Chest": null,
        "starterPack_Gold": null,
        "valueMultiplier": null,
        "appendArenaToChestName": null,
        "tiedToArenaUnlock": null,
        "repeatPurchaseGemPackOverride": null,
        "eventName": null,
        "costAdjustBasedOnChestContents": null,
        "isChronosOffer": "TRUE"
    },
    {
        "name": "ChronosOffer_6",
        "category": "Chronos",
        "tID": "Special Offer",
        "rarity": null,
        "disabled": null,
        "resource": null,
        "cost": null,
        "count": null,
        "cycleDuration": null,
        "cycleDeadzoneStart": null,
        "cycleDeadzoneEnd": null,
        "topSection": null,
        "specialOffer": null,
        "durationSecs": null,
        "availabilitySecs": null,
        "syncToShopCycle": null,
        "chest": null,
        "trophyLimit": null,
        "iAP": "com.supercell.scroll.specialoffertier6",
        "starterPack_Chest": null,
        "starterPack_Gold": null,
        "valueMultiplier": null,
        "appendArenaToChestName": null,
        "tiedToArenaUnlock": null,
        "repeatPurchaseGemPackOverride": null,
        "eventName": null,
        "costAdjustBasedOnChestContents": null,
        "isChronosOffer": "TRUE"
    },
    {
        "name": "ChronosOffer_7",
        "category": "Chronos",
        "tID": "Special Offer",
        "rarity": null,
        "disabled": null,
        "resource": null,
        "cost": null,
        "count": null,
        "cycleDuration": null,
        "cycleDeadzoneStart": null,
        "cycleDeadzoneEnd": null,
        "topSection": null,
        "specialOffer": null,
        "durationSecs": null,
        "availabilitySecs": null,
        "syncToShopCycle": null,
        "chest": null,
        "trophyLimit": null,
        "iAP": "com.supercell.scroll.specialoffertier7",
        "starterPack_Chest": null,
        "starterPack_Gold": null,
        "valueMultiplier": null,
        "appendArenaToChestName": null,
        "tiedToArenaUnlock": null,
        "repeatPurchaseGemPackOverride": null,
        "eventName": null,
        "costAdjustBasedOnChestContents": null,
        "isChronosOffer": "TRUE"
    },
    {
        "name": "ChronosOffer_8",
        "category": "Chronos",
        "tID": "Special Offer",
        "rarity": null,
        "disabled": null,
        "resource": null,
        "cost": null,
        "count": null,
        "cycleDuration": null,
        "cycleDeadzoneStart": null,
        "cycleDeadzoneEnd": null,
        "topSection": null,
        "specialOffer": null,
        "durationSecs": null,
        "availabilitySecs": null,
        "syncToShopCycle": null,
        "chest": null,
        "trophyLimit": null,
        "iAP": "com.supercell.scroll.specialoffertier8",
        "starterPack_Chest": null,
        "starterPack_Gold": null,
        "valueMultiplier": null,
        "appendArenaToChestName": null,
        "tiedToArenaUnlock": null,
        "repeatPurchaseGemPackOverride": null,
        "eventName": null,
        "costAdjustBasedOnChestContents": null,
        "isChronosOffer": "TRUE"
    },
    {
        "name": "ChronosOffer_9",
        "category": "Chronos",
        "tID": "Special Offer",
        "rarity": null,
        "disabled": null,
        "resource": null,
        "cost": null,
        "count": null,
        "cycleDuration": null,
        "cycleDeadzoneStart": null,
        "cycleDeadzoneEnd": null,
        "topSection": null,
        "specialOffer": null,
        "durationSecs": null,
        "availabilitySecs": null,
        "syncToShopCycle": null,
        "chest": null,
        "trophyLimit": null,
        "iAP": "com.supercell.scroll.specialoffertier9",
        "starterPack_Chest": null,
        "starterPack_Gold": null,
        "valueMultiplier": null,
        "appendArenaToChestName": null,
        "tiedToArenaUnlock": null,
        "repeatPurchaseGemPackOverride": null,
        "eventName": null,
        "costAdjustBasedOnChestContents": null,
        "isChronosOffer": "TRUE"
    },
    {
        "name": "ChronosOffer_10",
        "category": "Chronos",
        "tID": "Special Offer",
        "rarity": null,
        "disabled": null,
        "resource": null,
        "cost": null,
        "count": null,
        "cycleDuration": null,
        "cycleDeadzoneStart": null,
        "cycleDeadzoneEnd": null,
        "topSection": null,
        "specialOffer": null,
        "durationSecs": null,
        "availabilitySecs": null,
        "syncToShopCycle": null,
        "chest": null,
        "trophyLimit": null,
        "iAP": "com.supercell.scroll.specialoffertier10",
        "starterPack_Chest": null,
        "starterPack_Gold": null,
        "valueMultiplier": null,
        "appendArenaToChestName": null,
        "tiedToArenaUnlock": null,
        "repeatPurchaseGemPackOverride": null,
        "eventName": null,
        "costAdjustBasedOnChestContents": null,
        "isChronosOffer": "TRUE"
    },
    {
        "name": "ChronosOffer_15",
        "category": "Chronos",
        "tID": "Special Offer",
        "rarity": null,
        "disabled": null,
        "resource": null,
        "cost": null,
        "count": null,
        "cycleDuration": null,
        "cycleDeadzoneStart": null,
        "cycleDeadzoneEnd": null,
        "topSection": null,
        "specialOffer": null,
        "durationSecs": null,
        "availabilitySecs": null,
        "syncToShopCycle": null,
        "chest": null,
        "trophyLimit": null,
        "iAP": "com.supercell.scroll.specialoffertier15",
        "starterPack_Chest": null,
        "starterPack_Gold": null,
        "valueMultiplier": null,
        "appendArenaToChestName": null,
        "tiedToArenaUnlock": null,
        "repeatPurchaseGemPackOverride": null,
        "eventName": null,
        "costAdjustBasedOnChestContents": null,
        "isChronosOffer": "TRUE"
    },
    {
        "name": "ChronosOffer_20",
        "category": "Chronos",
        "tID": "Special Offer",
        "rarity": null,
        "disabled": null,
        "resource": null,
        "cost": null,
        "count": null,
        "cycleDuration": null,
        "cycleDeadzoneStart": null,
        "cycleDeadzoneEnd": null,
        "topSection": null,
        "specialOffer": null,
        "durationSecs": null,
        "availabilitySecs": null,
        "syncToShopCycle": null,
        "chest": null,
        "trophyLimit": null,
        "iAP": "com.supercell.scroll.specialoffertier20",
        "starterPack_Chest": null,
        "starterPack_Gold": null,
        "valueMultiplier": null,
        "appendArenaToChestName": null,
        "tiedToArenaUnlock": null,
        "repeatPurchaseGemPackOverride": null,
        "eventName": null,
        "costAdjustBasedOnChestContents": null,
        "isChronosOffer": "TRUE"
    },
    {
        "name": "ChronosOffer_50",
        "category": "Chronos",
        "tID": "Special Offer",
        "rarity": null,
        "disabled": null,
        "resource": null,
        "cost": null,
        "count": null,
        "cycleDuration": null,
        "cycleDeadzoneStart": null,
        "cycleDeadzoneEnd": null,
        "topSection": null,
        "specialOffer": null,
        "durationSecs": null,
        "availabilitySecs": null,
        "syncToShopCycle": null,
        "chest": null,
        "trophyLimit": null,
        "iAP": "com.supercell.scroll.specialoffertier50",
        "starterPack_Chest": null,
        "starterPack_Gold": null,
        "valueMultiplier": null,
        "appendArenaToChestName": null,
        "tiedToArenaUnlock": null,
        "repeatPurchaseGemPackOverride": null,
        "eventName": null,
        "costAdjustBasedOnChestContents": null,
        "isChronosOffer": "TRUE"
    },
    {
        "name": "ChronosOffer_60",
        "category": "Chronos",
        "tID": "Special Offer",
        "rarity": null,
        "disabled": null,
        "resource": null,
        "cost": null,
        "count": null,
        "cycleDuration": null,
        "cycleDeadzoneStart": null,
        "cycleDeadzoneEnd": null,
        "topSection": null,
        "specialOffer": null,
        "durationSecs": null,
        "availabilitySecs": null,
        "syncToShopCycle": null,
        "chest": null,
        "trophyLimit": null,
        "iAP": "com.supercell.scroll.specialoffertier60",
        "starterPack_Chest": null,
        "starterPack_Gold": null,
        "valueMultiplier": null,
        "appendArenaToChestName": null,
        "tiedToArenaUnlock": null,
        "repeatPurchaseGemPackOverride": null,
        "eventName": null,
        "costAdjustBasedOnChestContents": null,
        "isChronosOffer": "TRUE"
    },
    {
        "name": "StarterPackArenaT",
        "category": "StarterPack",
        "tID": "Legendary Arena Offer",
        "rarity": null,
        "disabled": null,
        "resource": "IAP",
        "cost": null,
        "count": null,
        "cycleDuration": 14,
        "cycleDeadzoneStart": 5,
        "cycleDeadzoneEnd": 5,
        "topSection": null,
        "specialOffer": "TRUE",
        "durationSecs": null,
        "availabilitySecs": null,
        "syncToShopCycle": null,
        "chest": null,
        "trophyLimit": 3800,
        "iAP": "com.supercell.scroll.consumablestarterpack8",
        "starterPack_Chest": "Draft_StarterPack_T",
        "starterPack_Gold": 100000,
        "valueMultiplier": 4,
        "appendArenaToChestName": null,
        "tiedToArenaUnlock": null,
        "repeatPurchaseGemPackOverride": "com.supercell.scroll.gempack2",
        "eventName": null,
        "costAdjustBasedOnChestContents": null,
        "isChronosOffer": null
    },
    {
        "name": "StarterPackArena1",
        "category": "StarterPack",
        "tID": "Goblin Stadium Starter Pack",
        "rarity": null,
        "disabled": "TRUE",
        "resource": "IAP",
        "cost": null,
        "count": null,
        "cycleDuration": 14,
        "cycleDeadzoneStart": 5,
        "cycleDeadzoneEnd": 5,
        "topSection": null,
        "specialOffer": "TRUE",
        "durationSecs": null,
        "availabilitySecs": null,
        "syncToShopCycle": null,
        "chest": null,
        "trophyLimit": 100,
        "iAP": "com.supercell.scroll.consumablestarterpack9",
        "starterPack_Chest": "Shop_Small_1_Arena1",
        "starterPack_Gold": 2000,
        "valueMultiplier": 4,
        "appendArenaToChestName": null,
        "tiedToArenaUnlock": null,
        "repeatPurchaseGemPackOverride": null,
        "eventName": null,
        "costAdjustBasedOnChestContents": null,
        "isChronosOffer": null
    },
    {
        "name": "StarterPackArena2",
        "category": "StarterPack",
        "tID": "Bone Pit Starter Pack",
        "rarity": null,
        "disabled": null,
        "resource": "IAP",
        "cost": null,
        "count": null,
        "cycleDuration": 14,
        "cycleDeadzoneStart": 5,
        "cycleDeadzoneEnd": 5,
        "topSection": null,
        "specialOffer": "TRUE",
        "durationSecs": null,
        "availabilitySecs": null,
        "syncToShopCycle": null,
        "chest": null,
        "trophyLimit": 400,
        "iAP": "com.supercell.scroll.consumablestarterpack10",
        "starterPack_Chest": "Shop_Small_1_Arena2",
        "starterPack_Gold": 2000,
        "valueMultiplier": 4,
        "appendArenaToChestName": null,
        "tiedToArenaUnlock": null,
        "repeatPurchaseGemPackOverride": null,
        "eventName": null,
        "costAdjustBasedOnChestContents": null,
        "isChronosOffer": null
    },
    {
        "name": "StarterPackArenaE",
        "category": "StarterPack",
        "tID": "Electro Valley Pack",
        "rarity": null,
        "disabled": null,
        "resource": "IAP",
        "cost": null,
        "count": null,
        "cycleDuration": 14,
        "cycleDeadzoneStart": 5,
        "cycleDeadzoneEnd": 5,
        "topSection": null,
        "specialOffer": "TRUE",
        "durationSecs": null,
        "availabilitySecs": null,
        "syncToShopCycle": null,
        "chest": null,
        "trophyLimit": 3400,
        "iAP": "com.supercell.scroll.consumablestarterpack11",
        "starterPack_Chest": "Shop_Large_Legendary_Arena_Electric",
        "starterPack_Gold": 50000,
        "valueMultiplier": 4,
        "appendArenaToChestName": null,
        "tiedToArenaUnlock": null,
        "repeatPurchaseGemPackOverride": null,
        "eventName": null,
        "costAdjustBasedOnChestContents": null,
        "isChronosOffer": null
    }
]